blob_detector
